pysofft-0.1.3.dist-info/METADATA
pysofft-0.1.3.dist-info/WHEEL
pysofft-0.1.3.dist-info/licenses/LICENSE
pysofft/__init__.py
pysofft/__pycache__/soft.Forward_SO3_Naive_fft_pc-570.py311.1.nbc
pysofft/__pycache__/soft.Forward_SO3_Naive_fft_pc-570.py311.nbi
pysofft/__pycache__/soft.Inverse_SO3_Naive_fft_pc-240.py311.1.nbc
pysofft/__pycache__/soft.Inverse_SO3_Naive_fft_pc-240.py311.nbi
pysofft/__pycache__/soft.Inverse_SO3_Naive_fft_pc-243.py311.1.nbc
pysofft/__pycache__/soft.Inverse_SO3_Naive_fft_pc-243.py311.nbi
pysofft/__pycache__/soft.coefLoc_so3-73.py311.1.nbc
pysofft/__pycache__/soft.coefLoc_so3-73.py311.nbi
pysofft/__pycache__/soft.coefLoc_so3-76.py311.1.nbc
pysofft/__pycache__/soft.coefLoc_so3-76.py311.nbi
pysofft/__pycache__/soft.howMany_so3-32.py311.1.nbc
pysofft/__pycache__/soft.howMany_so3-32.py311.nbi
pysofft/__pycache__/soft.howMany_so3-35.py311.1.nbc
pysofft/__pycache__/soft.howMany_so3-35.py311.nbi
pysofft/__pycache__/soft.inverse_wigner-1030.py311.1.nbc
pysofft/__pycache__/soft.inverse_wigner-1030.py311.nbi
pysofft/__pycache__/soft.inverse_wigner-1033.py311.1.nbc
pysofft/__pycache__/soft.inverse_wigner-1033.py311.nbi
pysofft/__pycache__/soft.sampLoc_so3-48.py311.1.nbc
pysofft/__pycache__/soft.sampLoc_so3-48.py311.nbi
pysofft/__pycache__/soft.sampLoc_so3-51.py311.1.nbc
pysofft/__pycache__/soft.sampLoc_so3-51.py311.nbi
pysofft/__pycache__/soft.totalCoeffs_so3-18.py311.1.nbc
pysofft/__pycache__/soft.totalCoeffs_so3-18.py311.nbi
pysofft/__pycache__/soft.totalCoeffs_so3-21.py311.1.nbc
pysofft/__pycache__/soft.totalCoeffs_so3-21.py311.nbi
pysofft/__pycache__/soft.wigLen_so3-175.py311.1.nbc
pysofft/__pycache__/soft.wigLen_so3-175.py311.nbi
pysofft/__pycache__/soft.wigLen_so3-178.py311.1.nbc
pysofft/__pycache__/soft.wigLen_so3-178.py311.nbi
pysofft/make_wiegner.py
pysofft/rotate.py
pysofft/soft.py
pysofft/wignerTransform.py
pysofft/wignerWeights.py
pysofft-0.1.3.dist-info/RECORD
