Metadata-Version: 2.1
Name: pysofft
Version: 0.1.3
Summary: Python port of the C library SOFT 2.0, that computes fourier transforms on the rotation group SO(3).
Keywords: SO(3) FFT fourier transform SOFT
Author-Email: Unknown <tim.berberich@xfel.eu>
Classifier: Intended Audience :: Developers
Classifier: License :: OSI Approved :: GNU General Public License v3 (GPLv3)
Classifier: Programming Language :: Python :: 3 :: Only
Project-URL: Homepage, https://github.com/TimBerberich/pysoft
Requires-Python: >=3.8
Requires-Dist: numba
Requires-Dist: numpy
